homemadeai/__init__.py
homemadeai/homemadeai.py
homemadeai-2.0.1.dist-info/LICENSE
homemadeai-2.0.1.dist-info/METADATA
homemadeai-2.0.1.dist-info/WHEEL
homemadeai-2.0.1.dist-info/top_level.txt
homemadeai-2.0.1.dist-info/RECORD
