Metadata-Version: 2.1
Name: homemadeai
Version: 2.0.1
Summary: a package for creating primitive AI nets.
Home-page: https://github.com/pypa/sampleproject
Author: anon
Author-email: daniel.varkin@gmail.com
License: UNKNOWN
Project-URL: Bug Tracker, https://github.com/pypa/sampleproject/issues
Platform: UNKNOWN
Classifier: Programming Language :: Python :: 3
Classifier: License :: OSI Approved :: MIT License
Classifier: Operating System :: OS Independent
Requires-Python: >=3.6
License-File: LICENSE
